{
    "caption": "A curious puppy watching a peaceful summer landscape. Tricolor Beagle puppy on a walk along the pond in the city Park. stock photography",
    "url": "https://thumbs.dreamstime.com/b/curious-puppy-watching-peaceful-summer-landscape-tricolor-beagle-puppy-walk-along-pond-city-park-curious-123706032.jpg",
    "key": "000006588",
    "status": "success",
    "error_message": null,
    "width": 256,
    "height": 256,
    "original_width": 800,
    "original_height": 517,
    "exif": "{\"Image XResolution\": \"72\", \"Image YResolution\": \"72\", \"Image ResolutionUnit\": \"Pixels/Inch\", \"Image YCbCrPositioning\": \"Centered\", \"Image Copyright\": \"Subcomandantemarcos | Dreamstime.com\"}",
    "sha256": "f92fea96d2aeb5e70db9984ba63551a999c107391bcb29309c16d5681f3f55b3"
}