{
    "caption": "Photographer <PERSON> took this picture of this group of elephants three days ago in Amboseli National Park Kenya led by two of the worlds biggest elephants - <PERSON> and <PERSON>. Wild Photography, Wildlife Photography, Animal Photography, Group Of Elephants, <PERSON>, Amazing Animals, African Elephant, My Favorite Image, Photos",
    "url": "https://i.pinimg.com/originals/91/af/1b/91af1b4f3a8a06061dc7511da6647d80.jpg",
    "key": "000004686",
    "status": "success",
    "error_message": null,
    "width": 256,
    "height": 256,
    "original_width": 3600,
    "original_height": 2005,
    "exif": "{}",
    "sha256": "07b70d2974e20bf67def13f3bd9636243bbd5bc691050ce5ad4c9f5cceb16b49"
}