{
    "caption": "Top view of little boy sits at a computer and holds a keyboard in his hands stock photography",
    "url": "https://thumbs.dreamstime.com/b/little-child-boy-sitting-computer-holding-keyboard-his-hands-view-above-close-up-top-view-top-view-little-170119122.jpg",
    "key": "000000708",
    "status": "success",
    "error_message": null,
    "width": 256,
    "height": 256,
    "original_width": 800,
    "original_height": 543,
    "exif": "{\"Image XResolution\": \"72\", \"Image YResolution\": \"72\", \"Image ResolutionUnit\": \"Pixels/Inch\", \"Image YCbCrPositioning\": \"Centered\", \"Image Copyright\": \"Serhii Liakhevych | Dreamstime.com\"}",
    "sha256": "dc80faba94c840436ee38b414741f4fe72f622b482befbda7c04fea50429578d"
}