{
    "caption": "Cute pug dog sleep rest in the bed and tongue sticking out in the lazy time stock photography",
    "url": "https://thumbs.dreamstime.com/b/cute-pug-dog-sleep-rest-bed-tongue-sticking-out-lazy-time-cute-pug-dog-sleep-rest-bed-tongue-sticking-out-154148732.jpg",
    "key": "000005418",
    "status": "success",
    "error_message": null,
    "width": 256,
    "height": 256,
    "original_width": 800,
    "original_height": 450,
    "exif": "{\"Image XResolution\": \"72\", \"Image YResolution\": \"72\", \"Image ResolutionUnit\": \"Pixels/Inch\", \"Image YCbCrPositioning\": \"Centered\", \"Image Copyright\": \"Teerachat Aebwanawong | Dreamstime.com\"}",
    "sha256": "6d7576eed18679c4b7185f2f78ddc69335d033dbbe1f6bd4c6cab9a1aca388f3"
}