{
    "caption": "An old man sits on the sidewalk, presumably in front of his house.",
    "url": "http://www.adventuresinfinite.com/wp-content/uploads/2016/12/P1040102.jpg",
    "key": "000006821",
    "status": "success",
    "error_message": null,
    "width": 256,
    "height": 256,
    "original_width": 1024,
    "original_height": 684,
    "exif": "{\"Image Make\": \"Panasonic\", \"Image Model\": \"DMC-TZ25\", \"Image Orientation\": \"Horizontal (normal)\", \"Image XResolution\": \"180\", \"Image YResolution\": \"180\", \"Image ResolutionUnit\": \"Pixels/Inch\", \"Image Software\": \"Ver.1.0\", \"Image DateTime\": \"2016:12:20 05:01:23\", \"Image Artist\": \"\", \"Image YCbCrPositioning\": \"Co-sited\", \"Image ExifOffset\": \"716\", \"Image PrintIM\": \"[0, 0, 0, 0, 0, 0, 0, 0, 0, 0, 0, 0, 0, 0, 0, 0, 0, 0, 0, 0, ... ]\", \"Image Tag 0xC6D2\": \"[0, 0, 0, 0, 0, 0, 0, 0, 0, 0, 0, 0, 0, 0, 0, 0, 0, 0, 0, 0, ... ]\", \"Image Tag 0xC6D3\": \"[0, 0, 0, 0, 0, 0, 0, 0, 0, 0, 0, 0, 0, 0, 0, 0, 0, 0, 0, 0, ... ]\", \"Thumbnail Compression\": \"JPEG (old-style)\", \"Thumbnail Orientation\": \"Horizontal (normal)\", \"Thumbnail XResolution\": \"180\", \"Thumbnail YResolution\": \"180\", \"Thumbnail ResolutionUnit\": \"Pixels/Inch\", \"Thumbnail JPEGInterchangeFormat\": \"11764\", \"Thumbnail JPEGInterchangeFormatLength\": \"7204\", \"Thumbnail YCbCrPositioning\": \"Co-sited\", \"EXIF ExposureTime\": \"1/80\", \"EXIF FNumber\": \"49/10\", \"EXIF ExposureProgram\": \"Program Normal\", \"EXIF ISOSpeedRatings\": \"320\", \"EXIF SensitivityType\": \"Standard Output Sensitivity\", \"EXIF ExifVersion\": \"\", \"EXIF DateTimeOriginal\": \"2016:12:20 05:01:23\", \"EXIF DateTimeDigitized\": \"2016:12:20 05:01:23\", \"EXIF ComponentsConfiguration\": \"\", \"EXIF CompressedBitsPerPixel\": \"4\", \"EXIF ExposureBiasValue\": \"0\", \"EXIF MaxApertureValue\": \"587/128\", \"EXIF MeteringMode\": \"Pattern\", \"EXIF LightSource\": \"Unknown\", \"EXIF Flash\": \"Flash did not fire, compulsory flash mode\", \"EXIF FocalLength\": \"16\", \"EXIF FlashPixVersion\": \"\", \"EXIF ColorSpace\": \"sRGB\", \"EXIF ExifImageWidth\": \"1024\", \"EXIF ExifImageLength\": \"684\", \"Interoperability InteroperabilityIndex\": \"R98\", \"Interoperability InteroperabilityVersion\": \"[0, 0, 0, 0]\", \"EXIF InteroperabilityOffset\": \"10910\", \"EXIF SensingMethod\": \"One-chip color area\", \"EXIF FileSource\": \"0\", \"EXIF SceneType\": \"0\", \"EXIF CustomRendered\": \"Custom\", \"EXIF ExposureMode\": \"Auto Exposure\", \"EXIF WhiteBalance\": \"Auto\", \"EXIF DigitalZoomRatio\": \"0\", \"EXIF FocalLengthIn35mmFilm\": \"100\", \"EXIF SceneCaptureType\": \"Standard\", \"EXIF GainControl\": \"High gain up\", \"EXIF Contrast\": \"Normal\", \"EXIF Saturation\": \"Normal\", \"EXIF Sharpness\": \"Normal\"}",
    "sha256": "a88ac9183d83704944f7c08a2f5119f39a5c06895696cf0ef8db79e2b7854d55"
}