{
    "caption": "Telephone handset surrounded by a telephone cord - icon. Graphic elements for your design. Telephone handset surrounded by a telephone cord - icon royalty free illustration",
    "url": "https://thumbs.dreamstime.com/b/telephone-handset-surrounded-cord-icon-graphic-elements-your-design-132884361.jpg",
    "key": "000006055",
    "status": "success",
    "error_message": null,
    "width": 256,
    "height": 256,
    "original_width": 800,
    "original_height": 800,
    "exif": "{\"Image XResolution\": \"72\", \"Image YResolution\": \"72\", \"Image ResolutionUnit\": \"Pixels/Inch\", \"Image YCbCrPositioning\": \"Centered\", \"Image Copyright\": \"Sviatlana Sheina | Dreamstime.com\"}",
    "sha256": "19b15486ef6aab614100614b95f20b8ba1c726478fba41aa5e37c2384c19aa05"
}