{
    "caption": "Pocket watch: unique Patek Philippe pocket watch with enamelled coat of arms, and a minute repeater, sold to <PERSON> in 1901, with a special original box, and trunk book excerpt - photo 1",
    "url": "https://veryimportantlot.com/cache/lot/184934/433076_1555953720-563x367_width_50.jpg?_=1555953720",
    "key": "000005413",
    "status": "success",
    "error_message": null,
    "width": 256,
    "height": 256,
    "original_width": 563,
    "original_height": 422,
    "exif": "{}",
    "sha256": "f3d7c5af0ddc7dd29c67d634a343efd7912f8dddb43a4255838428e4da83717d"
}