{
    "caption": "Created work space in the pantry Lunch Room, Break Room, Pantry Office, Space, Bed, Rooms, Furniture, Creative, Home Decor",
    "url": "https://i.pinimg.com/originals/45/23/b8/4523b8a25ea8644ab3d3963055aaaf3f.jpg",
    "key": "000001970",
    "status": "success",
    "error_message": null,
    "width": 256,
    "height": 256,
    "original_width": 2400,
    "original_height": 1600,
    "exif": "{}",
    "sha256": "887fa2e9f21b44017eca2501ec361b2799581ed1a26c3f0e40c07a4c22343f31"
}