{
    "caption": "Find Arabesque Vector Round Tile Element Hexagonal stock images in HD and millions of other royalty-free stock photos, illustrations and vectors in the Shutterstock collection. Thousands of new, high-quality pictures added every day. Tile Edge, Arabic Pattern, Islamic Patterns, Geometric Decor, Bag Design, Arabesque, Islamic Art, Morocco, Geometry",
    "url": "https://i.pinimg.com/originals/14/86/a0/1486a055fcf43cca7082f129df311332.jpg",
    "key": "000005617",
    "status": "success",
    "error_message": null,
    "width": 256,
    "height": 256,
    "original_width": 1500,
    "original_height": 1101,
    "exif": "{}",
    "sha256": "94c53ea185673f4859e91bf2710e0260c5f81ae7904f41bfeacb7db1fce8b540"
}