{
    "caption": "An Ancient Egyptian hieroglyphic carving of an eye surmounted by the zig zag line of water. Stone carving on a wall of the Temple of Horus at Edfu, Egypt.",
    "url": "https://image.shutterstock.com/image-photo/ancient-egyptian-hieroglyphic-carving-eye-600w-69081616.jpg",
    "key": "000003943",
    "status": "success",
    "error_message": null,
    "width": 256,
    "height": 256,
    "original_width": 600,
    "original_height": 419,
    "exif": "{}",
    "sha256": "702a16b321718bca12cf62c9ec36e8a6e2070d775fc03ab398aa3145a9ad6858"
}