{
    "caption": "Career Compass on how to become a Chef",
    "url": "https://slideplayer.com/slide/14359485/89/images/1/Career+Compass+on+how+to+become+a+Chef.jpg",
    "key": "000001852",
    "status": "success",
    "error_message": null,
    "width": 256,
    "height": 256,
    "original_width": 1024,
    "original_height": 576,
    "exif": "{\"Image DocumentName\": \"Career Compass on how to become a Chef\", \"Image ImageDescription\": \"By Isaac Code.\", \"Image XResolution\": \"200\", \"Image YResolution\": \"200\", \"Image ResolutionUnit\": \"Pixels/Inch\", \"Image Software\": \"SlidePlayer\", \"Image YCbCrPositioning\": \"Centered\"}",
    "sha256": "be67b5be8cb6248275e33b77deb98b5daa5bbc1f92d6527578af84490138ee17"
}