{
    "caption": "Help us save this incredibly intelligent Velociraptor (Jurassic World Fallen Kingdom) Velociraptor Jurassic World, Jurassic World Raptors, Jurassic Movies, Jurassic Park Series, Jurassic Park Party, Jurassic Park 1993, Blue Jurassic World, Jurassic World Fallen Kingdom, Raptor Dinosaur",
    "url": "https://i.pinimg.com/originals/25/15/71/251571bc103f57b41319c48a088e317c.jpg",
    "key": "000002287",
    "status": "success",
    "error_message": null,
    "width": 256,
    "height": 256,
    "original_width": 750,
    "original_height": 746,
    "exif": "{}",
    "sha256": "a47c8b7e334977ef52059c85862be0831ec3ef8d0318eb6fc5e96ca3a7edc8a5"
}