{
    "caption": "As you go into the restaurant, you would observe a great deal of warm colors that produce the entire space look very inviting and cozy. The restaurant wanted to have a logo design that could evoke the sensation of romance. Mexican Restaurant Design, Mexican Bar, Deco Restaurant, Mexican Restaurants, Restaurant Lighting, <PERSON>, Coffee Shop Design, Cafe Design, Caf\u00e9 Bar",
    "url": "https://i.pinimg.com/originals/ff/3a/d4/ff3ad4542c4b574fd8e85c3d5d5df7af.jpg",
    "key": "000005046",
    "status": "success",
    "error_message": null,
    "width": 256,
    "height": 256,
    "original_width": 3000,
    "original_height": 1772,
    "exif": "{}",
    "sha256": "99529844f86c5e0148872e9d0f6426b46eda308e2b1742eb664b868302353742"
}