{
    "caption": "Floral seamless white pattern with twigs and stripes on a gray background Vector. royalty free illustration",
    "url": "https://thumbs.dreamstime.com/b/floral-seamless-white-pattern-twigs-stripes-gray-background-floral-seamless-white-pattern-twigs-stripes-110239659.jpg",
    "key": "000007356",
    "status": "success",
    "error_message": null,
    "width": 256,
    "height": 256,
    "original_width": 800,
    "original_height": 800,
    "exif": "{\"Image XResolution\": \"72\", \"Image YResolution\": \"72\", \"Image ResolutionUnit\": \"Pixels/Inch\", \"Image YCbCrPositioning\": \"Centered\", \"Image Copyright\": \"Mielenna | Dreamstime.com\"}",
    "sha256": "706db795ba9c2b3d568be09d96a72319e523e1349ae36185acd1220155f5eb8c"
}