{
    "caption": "Photo of a elegant cream, white and yellow marquee wedding reception with covered chairs with yellow bows. Yellow Wedding, Wedding Colors, Wedding Themes, <PERSON>, Wedding Ideas, Gray Weddings, Elegant Wedding, Perfect Wedding, Dream Wedding",
    "url": "https://i.pinimg.com/originals/08/31/ce/0831ce8f1e7c33123efb014a6341e207.jpg",
    "key": "000006246",
    "status": "success",
    "error_message": null,
    "width": 256,
    "height": 256,
    "original_width": 560,
    "original_height": 420,
    "exif": "{}",
    "sha256": "3d3711bd840b8b6e2226d3eef82b0f6ebc453ecdf50241bf3270e2985f6ee2ee"
}