{
    "caption": "Take your nachos with you wherever you go with this edible hat. Just fill it up with salsa and wear it. If you get hungry, just start breaking pieces off Chip Hat, Guacamole Chips, Homemade Nachos, Crazy Hats, Chips And Salsa, Getting Hungry, Tortilla Chips, Halloween, Food Recipes",
    "url": "https://i.pinimg.com/originals/22/81/7a/22817ab269eef44195c6b5e6fd00c17d.jpg",
    "key": "000003709",
    "status": "success",
    "error_message": null,
    "width": 256,
    "height": 256,
    "original_width": 640,
    "original_height": 480,
    "exif": "{}",
    "sha256": "6b48001a5e2cd56089ca2b91ba1af8e5478d9a5ca9ba3729ea918ad3433ce0c5"
}