{
    "caption": "A <PERSON>. Signed Last Passport, Standard issue, obtained on Jul color - Available at 2016 November 12 Entertainment. Legal Separation, <PERSON>, Divorce Papers, Marriage Certificate, How To Remove, How To Get, <PERSON>, Mug Shots, Im In Love",
    "url": "https://i.pinimg.com/originals/e9/f1/17/e9f1173b8a8c6220bd7cdd5aac7d7edd.jpg",
    "key": "000001283",
    "status": "success",
    "error_message": null,
    "width": 256,
    "height": 256,
    "original_width": 2150,
    "original_height": 3000,
    "exif": "{}",
    "sha256": "651761139b6ff596600bb96be95bda66d4bb80e27467f0b81d8568d5d18ad074"
}