{
    "caption": "Flowering daisy (Bellis perennis) on a meadow, two flowers and one bud",
    "url": "https://media.gettyimages.com/photos/flowering-daisy-on-a-meadow-two-flowers-and-one-bud-picture-id1135623791?b=1&k=6&m=1135623791&s=612x612&w=0&h=Y2yzFhYe31-jZ1Dy3UYpLBAgbnGS1K3cCniSjlkidac=",
    "key": "000005784",
    "status": "success",
    "error_message": null,
    "width": 256,
    "height": 256,
    "original_width": 612,
    "original_height": 408,
    "exif": "{\"Image ImageDescription\": \"Daisies are composite flowers that can be found on almost all meadows. They were among the most membranous plants to be found in Central Europe. In naturopathy, daisies have been used since the 1st century A.D. - as an ointment against skin diseases, as a brew to stimulate digestion and urine formation, as a condition to stimulate healing of broken bones.\", \"Image XResolution\": \"300\", \"Image YResolution\": \"300\"}",
    "sha256": "2ae58a7d079bbdd5d56be29471c00e95e009b010078b01c2c8b1cc5aac8b4d94"
}