{
    "caption": "34 diy garden shade cloth greenhouse , consider your region and the type of plants that you should shade. it will be ideal for shade once the sun is in its greatest",
    "url": "https://i.pinimg.com/originals/bc/ef/c3/bcefc3f0d04cfe8b720c87f330c00d8e.jpg",
    "key": "000007971",
    "status": "success",
    "error_message": null,
    "width": 256,
    "height": 256,
    "original_width": 670,
    "original_height": 416,
    "exif": "{}",
    "sha256": "ade11f26a26630ae81a5c8f7520d0bf5442dfc390eb220254139451ffa1f182f"
}