{
    "caption": "Bali flyer with a girl. Swimming into the sea royalty free illustration",
    "url": "https://thumbs.dreamstime.com/b/bali-flyer-girl-swimming-sea-70849758.jpg",
    "key": "000003688",
    "status": "success",
    "error_message": null,
    "width": 256,
    "height": 256,
    "original_width": 800,
    "original_height": 800,
    "exif": "{\"Image XResolution\": \"72\", \"Image YResolution\": \"72\", \"Image ResolutionUnit\": \"Pixels/Inch\", \"Image YCbCrPositioning\": \"Centered\", \"Image Copyright\": \"Frimufilms | Dreamstime.com\"}",
    "sha256": "51837e0cffeac6297cb72c5d5380600155cc9d822fba18e5b9ddce8b20dc672c"
}