{
    "caption": "The white gopuram of the Sri Ranganathaswamy Temple in Trichy, southern India. This gopuram is part of the largest temple complex in India. The earliest parts of the temple date from the century. Indian Temple Architecture, Ancient Architecture, Architecture Details, Amazing Architecture, Temple India, Hindu Temple, Nova Deli, World Famous Buildings, Ufo",
    "url": "https://i.pinimg.com/originals/a3/6c/94/a36c9476e0bf240974ce126593ef5235.jpg",
    "key": "000007089",
    "status": "success",
    "error_message": null,
    "width": 256,
    "height": 256,
    "original_width": 427,
    "original_height": 640,
    "exif": "{}",
    "sha256": "60571828b98f112bfdd695a31a99076f474f6a26e03bf772ebdd6ce2a0212a41"
}