{
    "caption": "Sunset Through Smoke From A Fire stock photography",
    "url": "https://thumbs.dreamstime.com/b/sunset-smoke-fire-sun-cloud-forest-100183932.jpg",
    "key": "000009283",
    "status": "success",
    "error_message": null,
    "width": 256,
    "height": 256,
    "original_width": 800,
    "original_height": 534,
    "exif": "{\"Image XResolution\": \"72\", \"Image YResolution\": \"72\", \"Image ResolutionUnit\": \"Pixels/Inch\", \"Image YCbCrPositioning\": \"Centered\", \"Image Copyright\": \"Sonsam | Dreamstime.com\"}",
    "sha256": "2321f67f99c4732d51db36b304895c7880f321d3ad676f6f73e4ea8805660bbc"
}