{
    "caption": "While you think actress <PERSON> only had a stint on ``A Different World'' and some other shows, she's actually been working since age 11 Black Girls Rock, Black Girl Magic, <PERSON>, Black Pride, My Black Is Beautiful, <PERSON>, Black Power, Actors, <PERSON>",
    "url": "https://i.pinimg.com/originals/69/c5/19/69c51937c597f84efbfca4293823ee15.jpg",
    "key": "000002229",
    "status": "success",
    "error_message": null,
    "width": 256,
    "height": 256,
    "original_width": 960,
    "original_height": 722,
    "exif": "{}",
    "sha256": "c608d07a239262731a2fc5ba913032e57c94b94e15bd63dea3892c606a4a8c9a"
}