{
    "caption": "Empty runway at the airport stock photos",
    "url": "https://thumbs.dreamstime.com/b/empty-runway-airport-new-york-usa-oct-air-traffic-control-tower-terminal-air-planes-gates-jfk-ny-was-77270713.jpg",
    "key": "000003846",
    "status": "success",
    "error_message": null,
    "width": 256,
    "height": 256,
    "original_width": 800,
    "original_height": 402,
    "exif": "{\"Image XResolution\": \"72\", \"Image YResolution\": \"72\", \"Image ResolutionUnit\": \"Pixels/Inch\", \"Image YCbCrPositioning\": \"Centered\", \"Image Copyright\": \"Meinzahn | Dreamstime.com\"}",
    "sha256": "411a96b75b5c750b389aa92b562707697043ee6b8299a463b8be154f78b2dee4"
}