{
    "caption": "Cool Art: The Black Keys Gig Posters by <PERSON>, Band Posters, Musik Illustration, Graphic Design Illustration, Digital Illustration, Retro Poster, Vintage Posters, Gig Poster, <PERSON>",
    "url": "https://i.pinimg.com/originals/54/f7/9e/54f79e7845f2af67ea4ec59a3b60ae06.jpg",
    "key": "000002334",
    "status": "success",
    "error_message": null,
    "width": 256,
    "height": 256,
    "original_width": 1200,
    "original_height": 1690,
    "exif": "{}",
    "sha256": "ef1e7657ca28a061e8bda4c7a0bdd7b5bf5836145a07db3525c67079eb9ca6a6"
}