{
    "caption": "Is there ever a time <PERSON> doesn't look incredible? We adore that maroon skater skirt! Street Look, Street Style, <PERSON>, Disney Queens, Cute Hairstyles, Skater Skirt, Curly Hair Styles, Most Beautiful, Cute Outfits",
    "url": "https://i.pinimg.com/originals/7e/2a/39/7e2a3939a1f17bfbf6b21e473d9a9444.jpg",
    "key": "000000229",
    "status": "success",
    "error_message": null,
    "width": 256,
    "height": 256,
    "original_width": 460,
    "original_height": 615,
    "exif": "{}",
    "sha256": "ba20131d65c685adf91691894dbf121588263a99a8047fb6253792a79313276f"
}