{
    "caption": "Some people spend months planning their wedding. They try to control everything down to the last detail. For them, the wedding has to be perfect and everything about the wedding including the dress and the Wedding Dress Fails, Funny Wedding Dresses, Wedding Fail, Wedding Humor, Epic Fail Photos, Funny Fails, Lace Dress, <PERSON>, Funny Pictures",
    "url": "https://i.pinimg.com/originals/cd/5f/9d/cd5f9ded334167846666191f3a829027.jpg",
    "key": "000001914",
    "status": "success",
    "error_message": null,
    "width": 256,
    "height": 256,
    "original_width": 1000,
    "original_height": 2098,
    "exif": "{}",
    "sha256": "a3e45a4e44d43e7f0d140a2aa8d3a734072fefcd343330c6c367569d219352f4"
}