{
    "caption": "The dog face monogram logo inspiration. Isolated on white background royalty free illustration",
    "url": "https://thumbs.dreamstime.com/b/dog-face-monogram-logo-inspiration-isolated-white-background-136659342.jpg",
    "key": "000006136",
    "status": "success",
    "error_message": null,
    "width": 256,
    "height": 256,
    "original_width": 800,
    "original_height": 800,
    "exif": "{\"Image XResolution\": \"72\", \"Image YResolution\": \"72\", \"Image ResolutionUnit\": \"Pixels/Inch\", \"Image YCbCrPositioning\": \"Centered\", \"Image Copyright\": \"Ananto Nooraini Putro | Dreamstime.com\"}",
    "sha256": "fa2b7bd18d8d975208aa649ac9f405ff2a35250a759d18ac320aa1089468dbf7"
}