{
    "caption": "Copenhagen's Nikolaj Kunsthal Tower is sporting a pink ring.",
    "url": "https://lp-cms-production.imgix.net/news/2018/07/Nikolaj-Kunsthal-Tower.jpg?auto=format&fit=crop&q=40&sharp=10&vib=20&ixlib=react-8.6.4",
    "key": "000007829",
    "status": "success",
    "error_message": null,
    "width": 256,
    "height": 256,
    "original_width": 2000,
    "original_height": 3000,
    "exif": "{}",
    "sha256": "1c0d472ee5abe88c05a915f074182b5e14c879af001209b652fb54aafa08b41d"
}