{
    "caption": "Drawing of a scientist thinking in data, a citizen thinking empathy to a flooded person and planet Earth thinking a heart. Illustration by <PERSON>",
    "url": "https://hikingorg.files.wordpress.com/2019/10/illustration-mindset-citizen-science-planet-frits-ahlefeldt-txt-heart.jpg?w=600",
    "key": "000000611",
    "status": "success",
    "error_message": null,
    "width": 256,
    "height": 256,
    "original_width": 600,
    "original_height": 600,
    "exif": "{}",
    "sha256": "4248fdda1ac80088b29291564a0c3605ad2870d1ca19966a183705ed6ebab795"
}