{
    "caption": "<PERSON> in <PERSON> at the London premiere of Wish I was Here",
    "url": "http://www.fashiontrendsdaily.com/wp-content/uploads/2014/09/1411141489_kate-hudson-zoom.jpg",
    "key": "000003704",
    "status": "success",
    "error_message": null,
    "width": 256,
    "height": 256,
    "original_width": 927,
    "original_height": 561,
    "exif": "{\"Image Orientation\": \"Horizontal (normal)\", \"Image XResolution\": \"72\", \"Image YResolution\": \"72\", \"Image ResolutionUnit\": \"Pixels/Inch\", \"Image Software\": \"Adobe Photoshop CS6 Macintosh\", \"Image Artist\": \"Dave J Hogan\", \"Image Copyright\": \"2014 Dave J Hogan\", \"Image ExifOffset\": \"188\", \"EXIF ColorSpace\": \"sRGB\", \"EXIF ExifImageWidth\": \"927\", \"EXIF ExifImageLength\": \"561\"}",
    "sha256": "fc2a4b788a2f15a60f22025afd67cc7da2759489236bf17760fe2fb3a7936caf"
}