{
    "caption": "Logo of a sports team. A bull with a nose ring. Vector illustration royalty free illustration",
    "url": "https://thumbs.dreamstime.com/b/logo-sports-team-bull-nose-ring-vector-illustration-171207831.jpg",
    "key": "000003752",
    "status": "success",
    "error_message": null,
    "width": 256,
    "height": 256,
    "original_width": 782,
    "original_height": 900,
    "exif": "{\"Image XResolution\": \"72\", \"Image YResolution\": \"72\", \"Image ResolutionUnit\": \"Pixels/Inch\", \"Image YCbCrPositioning\": \"Centered\", \"Image Copyright\": \"Alexverrone | Dreamstime.com\"}",
    "sha256": "70e6df0d7e7d6bf7306ebbb1e4aabe5b603ba07fecb95fea1ddf96a2e04c3954"
}