{
    "caption": "Vertical frame American flag flying from a front porch of a house. In a long receding row of urban properties on a quiet street stock photos",
    "url": "https://thumbs.dreamstime.com/b/vertical-frame-american-flag-flying-front-porch-house-long-receding-row-urban-properties-quiet-street-168714533.jpg",
    "key": "000009324",
    "status": "success",
    "error_message": null,
    "width": 256,
    "height": 256,
    "original_width": 506,
    "original_height": 900,
    "exif": "{\"Image XResolution\": \"72\", \"Image YResolution\": \"72\", \"Image ResolutionUnit\": \"Pixels/Inch\", \"Image YCbCrPositioning\": \"Centered\", \"Image Copyright\": \"Jason Finn | Dreamstime.com\"}",
    "sha256": "3b11a468f91cb74b61eed92c57f00daef2e11bb903f2dba3bf818def62c8a034"
}