{
    "caption": "Young hacker little girl in glasses with a school backpack working at the computer, laptop. stock images",
    "url": "https://thumbs.dreamstime.com/b/young-hacker-little-girl-glasses-school-backpack-working-computer-laptop-133910974.jpg",
    "key": "000007106",
    "status": "success",
    "error_message": null,
    "width": 256,
    "height": 256,
    "original_width": 800,
    "original_height": 534,
    "exif": "{\"Image XResolution\": \"72\", \"Image YResolution\": \"72\", \"Image ResolutionUnit\": \"Pixels/Inch\", \"Image YCbCrPositioning\": \"Centered\", \"Image Copyright\": \"Valerii Honcharuk | Dreamstime.com\"}",
    "sha256": "ec8ce835908ca65930d78bcfa2d87461150bb3169d0ebfc7123a5d27a3ddb966"
}