{
    "caption": "Clare elementary small division celebrate their win at the 2015 CYO Cheerleading championship at the College of Staten Island in Willowbrook. College Of Staten Island, March 21, <PERSON>, Division, Cheerleading, Champion, Celebrities, Celebs, Cheer",
    "url": "https://i.pinimg.com/originals/eb/1b/85/eb1b8535c6f7ebc012b6e8d448f8f6be.jpg",
    "key": "000006163",
    "status": "success",
    "error_message": null,
    "width": 256,
    "height": 256,
    "original_width": 564,
    "original_height": 450,
    "exif": "{}",
    "sha256": "b2c2a7ae33927444df2f75c1cf205f2ca0fcab1829ab4164f31637b43cbef7dc"
}