{
    "caption": "The Artisan Painted Tall Dresser Storage Unit",
    "url": "https://cdn.shopify.com/s/files/1/0018/5525/8668/products/IMG_6410_512x683.jpg?v=1522846839",
    "key": "000004047",
    "status": "success",
    "error_message": null,
    "width": 256,
    "height": 256,
    "original_width": 512,
    "original_height": 683,
    "exif": "{\"Image Orientation\": \"Horizontal (normal)\", \"Image XResolution\": \"72\", \"Image YResolution\": \"72\", \"Image ResolutionUnit\": \"Pixels/Inch\", \"Image YCbCrPositioning\": \"Centered\", \"Image ExifOffset\": \"102\", \"EXIF ExifVersion\": \"\", \"EXIF ComponentsConfiguration\": \"\", \"EXIF FlashPixVersion\": \"\", \"EXIF ColorSpace\": \"Uncalibrated\", \"EXIF ExifImageWidth\": \"512\", \"EXIF ExifImageLength\": \"683\"}",
    "sha256": "556ef7616df82c31adada0edf7e548470e447eec353b1526e673cd1580d8a2aa"
}