{
    "caption": "Blue Terminal logo in white on business cards featuring geyser, oil extraction, nuclear power plant and green luscious groves of a tea plantation -- by <PERSON>.",
    "url": "https://uploads-ssl.webflow.com/5c8da6fd4e2db8980aaff4c8/5dd384a558fd7f2e0ccd0886_bt-crds.jpg",
    "key": "000006167",
    "status": "success",
    "error_message": null,
    "width": 256,
    "height": 256,
    "original_width": 985,
    "original_height": 755,
    "exif": "{}",
    "sha256": "e2e94abd289853fe557453c0737d6ec8b95fec02ed07f858aa0016f67fe8655a"
}