{
    "caption": "Style Icon - Sir <PERSON> - The China Club and Shanghai Tang. Shanghai Tang, Global Style, <PERSON>, Style Icons, Gentleman, Decorating Ideas, <PERSON>, Bohemian, Classy",
    "url": "https://i.pinimg.com/originals/c1/bc/dd/c1bcdd3569c34e563171c17838625260.jpg",
    "key": "000009717",
    "status": "success",
    "error_message": null,
    "width": 256,
    "height": 256,
    "original_width": 489,
    "original_height": 557,
    "exif": "{}",
    "sha256": "a67852e866b28a3ae7504229b9f5c4b71420b445478771483df95322db2457fc"
}