{
    "caption": "Human Flag 2 Face USA. Torn and Flag of world flag wave on a face of a model stock illustration",
    "url": "https://thumbs.dreamstime.com/b/human-flag-face-usa-torn-world-wave-model-118588798.jpg",
    "key": "000008299",
    "status": "success",
    "error_message": null,
    "width": 256,
    "height": 256,
    "original_width": 800,
    "original_height": 509,
    "exif": "{\"Image XResolution\": \"72\", \"Image YResolution\": \"72\", \"Image ResolutionUnit\": \"Pixels/Inch\", \"Image YCbCrPositioning\": \"Centered\", \"Image Copyright\": \"Tugrul Soysal | Dreamstime.com\"}",
    "sha256": "5ed7c9ab7d826245076a1d5441cd7f13a29e69fdd67bec5b76fa7fd16bff0985"
}