{
    "caption": "Sunset sailing in the Caribbean sea off the coast of Oranjestad, Aruba. Colour Inspiration, Tattoo Inspiration, Amazing Pics, Awesome, Oranjestad, Tattoo Now, Caribbean Sea, Future Travel, Natural Wonders",
    "url": "https://i.pinimg.com/originals/ec/31/8b/ec318b6356fde3beb84667a40446d4b6.jpg",
    "key": "000001484",
    "status": "success",
    "error_message": null,
    "width": 256,
    "height": 256,
    "original_width": 900,
    "original_height": 600,
    "exif": "{}",
    "sha256": "d902f1b4bc16b9c60673f84f2548cc5cefa824a9ad9f655530f5c46e2b94623a"
}