{
    "caption": "<PERSON> and <PERSON>. <PERSON> and <PERSON> at the Los Angeles premiere of 'Haywire' held at the DGA Theater in Hollywood on January 5, 2012 stock images",
    "url": "https://thumbs.dreamstime.com/b/channing-tatum-gina-carano-los-angeles-premiere-haywire-held-dga-theater-hollywood-january-56832024.jpg",
    "key": "000003132",
    "status": "success",
    "error_message": null,
    "width": 256,
    "height": 256,
    "original_width": 613,
    "original_height": 900,
    "exif": "{\"Image XResolution\": \"72\", \"Image YResolution\": \"72\", \"Image ResolutionUnit\": \"Pixels/Inch\", \"Image YCbCrPositioning\": \"Centered\", \"Image Copyright\": \"Starstock | Dreamstime.com\"}",
    "sha256": "04947b8672806dd53c86dd3b8ce2cf8ec61ceae677b543f715e473bc8d5d27dc"
}