{
    "caption": "Many cars are driving at night on a highway and create light trails",
    "url": "https://thumbs.dreamstime.com/b/many-cars-driving-night-highway-create-light-trails-coloured-car-beam-road-great-effect-138762135.jpg",
    "key": "000004134",
    "status": "success",
    "error_message": null,
    "width": 256,
    "height": 256,
    "original_width": 800,
    "original_height": 534,
    "exif": "{\"Image XResolution\": \"72\", \"Image YResolution\": \"72\", \"Image ResolutionUnit\": \"Pixels/Inch\", \"Image YCbCrPositioning\": \"Centered\", \"Image Copyright\": \"Magdiel Lopez | Dreamstime.com\"}",
    "sha256": "95a75bcd48db5de7627fe4d179144cb719f8c3740ea3407667ee9c6315b7fb08"
}