{
    "caption": "Create a beautiful centerpiece for your home with this simple spring butterfly cloche decor idea. Just add flowers, moss and butterflies!",
    "url": "http://twopurplecouches.com/wp-content/uploads/2017/03/simple-springtime-butterfly-cloche-decor.jpg",
    "key": "000006911",
    "status": "success",
    "error_message": null,
    "width": 256,
    "height": 256,
    "original_width": 750,
    "original_height": 1500,
    "exif": "{\"Image XResolution\": \"300\", \"Image YResolution\": \"300\", \"Image ResolutionUnit\": \"Not Absolute\", \"Image Software\": \"Embettered by PicMonkey. http://www.picmonkey.com\", \"Image YCbCrPositioning\": \"Centered\"}",
    "sha256": "30319b66942fa9c393bbdd5b51edf62ada74ee712ff5ddfb7fa295ded6aed46a"
}