{
    "caption": "<PERSON> and <PERSON> merged. Made into a poster. Military Decorations, Volunteers, Ministry, Christianity, Army, Children, Poster, <PERSON>, <PERSON>",
    "url": "https://i.pinimg.com/originals/3d/a1/a3/3da1a3397437f40b89ba67e7344c9b4a.jpg",
    "key": "000007160",
    "status": "success",
    "error_message": null,
    "width": 256,
    "height": 256,
    "original_width": 768,
    "original_height": 1024,
    "exif": "{}",
    "sha256": "9d790f39f4e917699428a95e13f70e1bb1270ec5092597010295dcecf5738f18"
}