{
    "caption": "The New Perth Museum - Hera Engineering",
    "url": "https://i1.wp.com/hera.net.au/wp-content/uploads/2-State-Library-Francis-St.jpg",
    "key": "000009398",
    "status": "success",
    "error_message": null,
    "width": 256,
    "height": 256,
    "original_width": 1440,
    "original_height": 900,
    "exif": "{\"Image Orientation\": \"Horizontal (normal)\", \"Image XResolution\": \"72\", \"Image YResolution\": \"72\", \"Image ResolutionUnit\": \"Pixels/Inch\", \"Image Software\": \"Adobe Photoshop CS6 (Windows)\", \"Image DateTime\": \"2016:07:01 12:16:21\", \"Image ExifOffset\": \"164\", \"Thumbnail Compression\": \"JPEG (old-style)\", \"Thumbnail XResolution\": \"72\", \"Thumbnail YResolution\": \"72\", \"Thumbnail ResolutionUnit\": \"Pixels/Inch\", \"Thumbnail JPEGInterchangeFormat\": \"302\", \"Thumbnail JPEGInterchangeFormatLength\": \"5826\", \"EXIF ColorSpace\": \"Uncalibrated\", \"EXIF ExifImageWidth\": \"5000\", \"EXIF ExifImageLength\": \"3536\"}",
    "sha256": "9ea880e9b5ed12a1a5d3e15335a135e29c241becb3f301fd4fcb80e100d5672f"
}