{
    "caption": "Raffles City, Shenzhen, China - Located in the Nanshan area, the new creative... China Architecture, Futuristic Architecture, Concept Architecture, Facade Architecture, Residential Architecture, Mix Use Building, Tower Building, Building Facade, Building Design",
    "url": "https://i.pinimg.com/originals/e6/ae/86/e6ae8659f689ffcb3768d6f0657903cc.jpg",
    "key": "000000772",
    "status": "success",
    "error_message": null,
    "width": 256,
    "height": 256,
    "original_width": 2000,
    "original_height": 1278,
    "exif": "{}",
    "sha256": "b7b071497bcea6f8a879bbdfe5277e0b4f0bcbf069b1cf7f191db38602551064"
}